Metadata-Version: 2.1
Name: frankleetp
Version: 0.0.1
Summary: test pypi
Home-page: https://github.com/
Author: frank
Author-email: frankleecsz@gmail.com
License: UNKNOWN
Platform: UNKNOWN
Classifier: Programming Language :: Python :: 3
Classifier: License :: OSI Approved :: MIT License
Classifier: Operating System :: OS Independent
